config_framework/__init__.py
config_framework/py.typed
config_framework/loaders/__init__.py
config_framework/loaders/composite.py
config_framework/loaders/dict.py
config_framework/loaders/env.py
config_framework/loaders/json.py
config_framework/loaders/json_string.py
config_framework/loaders/toml_full_features.py
config_framework/loaders/toml_read_only.py
config_framework/loaders/yaml.py
config_framework/types/__init__.py
config_framework/types/config.py
config_framework/types/custom_exceptions.py
config_framework/types/variable.py
config_framework/types/variable_key.py
config_framework/types/abstract/__init__.py
config_framework/types/abstract/loader.py
config_framework/utils/__init__.py
config_framework/utils/loader_specific_deserializer.py
config_framework/utils/loader_specific_serializer.py
ConfigFramework-4.1.0.dist-info/LICENSE
ConfigFramework-4.1.0.dist-info/METADATA
ConfigFramework-4.1.0.dist-info/WHEEL
ConfigFramework-4.1.0.dist-info/top_level.txt
ConfigFramework-4.1.0.dist-info/RECORD
