Metadata-Version: 2.1
Name: ConfigFramework
Version: 4.1.0
Summary: A small framework to build your flexible project configurations
Home-page: https://github.com/Rud356/ConfigFramework
Author: Rud356
Author-email: Rud356 <rud356github@gmail.com>
License: MIT License
Keywords: config,configuration,config managment,configuration managment
Classifier: Programming Language :: Python :: 3.7
Classifier: Programming Language :: Python :: 3.8
Classifier: Programming Language :: Python :: 3.9
Classifier: Programming Language :: Python :: 3.10
Classifier: Programming Language :: Python :: 3.11
Classifier: Programming Language :: Python :: 3.12
Classifier: Programming Language :: Python :: 3.13
Classifier: Programming Language :: Python :: Implementation :: CPython
Classifier: Programming Language :: Python :: Implementation :: PyPy
Classifier: License :: OSI Approved :: MIT License
Classifier: Operating System :: OS Independent
Classifier: Intended Audience :: Developers
Classifier: Natural Language :: English
Requires-Python: >=3.7
License-File: LICENSE
Requires-Dist: pyyaml>=6.0.0
Provides-Extra: mypy
Requires-Dist: mypy; extra == "mypy"
Requires-Dist: types-PyYAML; extra == "mypy"
Requires-Dist: types-toml; extra == "mypy"
Provides-Extra: toml
Requires-Dist: toml; extra == "toml"
Provides-Extra: dev
Requires-Dist: sphinx~=5.0.2; extra == "dev"
Requires-Dist: sphinx-rtd-theme~=1.0.0; extra == "dev"
Requires-Dist: Pygments~=2.12.0; extra == "dev"
